hatch_project_name/__about__.py
hatch_project_name/__init__.py
hatch_project_name/hooks.py
hatch_project_name/plugin.py
hatch_project_name/py.typed
hatch_project_name-1.0.2.dist-info/METADATA
hatch_project_name-1.0.2.dist-info/WHEEL
hatch_project_name-1.0.2.dist-info/entry_points.txt
hatch_project_name-1.0.2.dist-info/licenses/LICENSE.txt
hatch_project_name-1.0.2.dist-info/RECORD
