Metadata-Version: 2.4
Name: hatch-project-name
Version: 1.0.2
Summary: Hatch build hook plugin that writes the project name to a file
Project-URL: History, https://github.com/valentinoli/hatch-project-name/blob/main/HISTORY.md
Project-URL: Issues, https://github.com/valentinoli/hatch-project-name/issues
Project-URL: Source, https://github.com/valentinoli/hatch-project-name
Author-email: Valentin Oliver Melberg Loftsson <valentin.loftsson@gmail.com>
License-File: LICENSE.txt
Keywords: git,hatch,mercurial,plugin
Classifier: Development Status :: 4 - Beta
Classifier: Framework :: Hatch
Classifier: Operating System :: OS Independent
Classifier: Programming Language :: Python
Classifier: Programming Language :: Python :: 3.11
Classifier: Programming Language :: Python :: 3.12
Classifier: Programming Language :: Python :: 3.13
Classifier: Programming Language :: Python :: Implementation :: CPython
Classifier: Programming Language :: Python :: Implementation :: PyPy
Requires-Python: >=3.11
Requires-Dist: hatchling>=1.1.0
